acem/__init__.py
acem/maths.py
acem/media.py
acem/model.py
acem/pdg.py
acem/util.py
acem/resources/ltot/ELECTRON.npz
acem/resources/ltot/KAON+.npz
acem/resources/ltot/KAONLONG.npz
acem/resources/ltot/KAONSHRT.npz
acem/resources/ltot/LAMBDA.npz
acem/resources/ltot/NEUTRON.npz
acem/resources/ltot/OMEGA-.npz
acem/resources/ltot/PHOTON.npz
acem/resources/ltot/PION+.npz
acem/resources/ltot/PROTON.npz
acem/resources/ltot/SIGMA+.npz
acem/resources/ltot/SIGMA-.npz
acem/resources/ltot/XSI-.npz
acem/resources/ltot/XSIZERO.npz
acem/resources/theta/ELECTRON.npz
acem/resources/theta/KAON+.npz
acem/resources/theta/KAONLONG.npz
acem/resources/theta/KAONSHRT.npz
acem/resources/theta/LAMBDA.npz
acem/resources/theta/NEUTRON.npz
acem/resources/theta/OMEGA-.npz
acem/resources/theta/PHOTON.npz
acem/resources/theta/PION+.npz
acem/resources/theta/PROTON.npz
acem/resources/theta/SIGMA+.npz
acem/resources/theta/SIGMA-.npz
acem/resources/theta/XSI-.npz
acem/resources/theta/XSIZERO.npz
acem-0.1.0.post1.dist-info/licenses/LICENSE
acem-0.1.0.post1.dist-info/METADATA
acem-0.1.0.post1.dist-info/WHEEL
acem-0.1.0.post1.dist-info/top_level.txt
acem-0.1.0.post1.dist-info/RECORD
