Metadata-Version: 2.4
Name: acem
Version: 0.1.0.post1
Summary: Approximations of Cherenkov yields for particle showers
Author-email: Ian Crawshaw <icrawshaw@wisc.edu>, Tianlu Yuan <tyuan@icecube.wisc.edu>
Maintainer-email: Tianlu Yuan <tyuan@icecube.wisc.edu>
License: BSD 2-Clause License
Project-URL: Repository, https://github.com/tianluyuan/acem
Classifier: Intended Audience :: Science/Research
Classifier: License :: OSI Approved :: BSD License
Classifier: Natural Language :: English
Classifier: Programming Language :: Python :: 3
Classifier: Topic :: Scientific/Engineering
Requires-Python: >=3.10
License-File: LICENSE
Requires-Dist: numpy>=1.17
Requires-Dist: scipy>=1.4
Provides-Extra: misc
Requires-Dist: matplotlib>=3.2; extra == "misc"
Requires-Dist: pandas; extra == "misc"
Requires-Dist: pythia8mc; extra == "misc"
Provides-Extra: test
Requires-Dist: pytest; extra == "test"
Dynamic: license-file
